changelog_version_bump/__init__.py
changelog_version_bump/changelog.py
changelog_version_bump/check_for_approvers/__init__.py
changelog_version_bump/check_for_approvers/cli.py
changelog_version_bump/delete_folder/__init__.py
changelog_version_bump/delete_folder/cli.py
changelog_version_bump/remove_comments/__init__.py
changelog_version_bump/remove_comments/cli.py
changelog_version_bump-0.4.9.dist-info/licenses/LICENSE
changelog_version_bump-0.4.9.dist-info/METADATA
changelog_version_bump-0.4.9.dist-info/WHEEL
changelog_version_bump-0.4.9.dist-info/entry_points.txt
changelog_version_bump-0.4.9.dist-info/top_level.txt
changelog_version_bump-0.4.9.dist-info/RECORD
