Metadata-Version: 2.4
Name: changelog-version-bump
Version: 0.4.9
Summary: A CLI tool to detect version labels in temp.md
Author-email: Richard Oberdieck <rico@bankingcircle.com>, Ruben Menke <rum@bankingcircle.com>
Requires-Python: >=3.7
License-File: LICENSE
Dynamic: license-file
